npttf2utf/__init__.py
npttf2utf/__main__.py
npttf2utf/map.json
npttf2utf/base/__init__.py
npttf2utf/base/docxhandler.py
npttf2utf/base/fontmapper.py
npttf2utf/base/preetimapper.py
npttf2utf/base/txthandler.py
npttf2utf/base/exceptions/__init__.py
npttf2utf-0.3.7.dist-info/LICENSE
npttf2utf-0.3.7.dist-info/METADATA
npttf2utf-0.3.7.dist-info/WHEEL
npttf2utf-0.3.7.dist-info/entry_points.txt
npttf2utf-0.3.7.dist-info/top_level.txt
npttf2utf-0.3.7.dist-info/RECORD
