Metadata-Version: 2.1
Name: npttf2utf
Version: 0.3.7
Summary: Python module/script to map Nepali ASCII font faces like Preeti, Sagarmatha, and more to devanagari unicode with direct mapping support for docx and txt files.
Home-page: https://github.com/trippygeese/npttf2utf
Author: Sabin Acharya
Author-email: sabin2059@protonmail.com
License: GPL-3.0 License
Keywords: nepali unicode converter,unicode to preeti,preeti to unicode
Platform: UNKNOWN
Requires-Python: >=3.0
